LICENSE
MANIFEST.in
README.md
attack_surface_meter.py
setup.py
attacksurfacemeter/__init__.py
attacksurfacemeter/android_call_graph.py
attacksurfacemeter/call.py
attacksurfacemeter/call_graph.py
attacksurfacemeter/environments.py
attacksurfacemeter/granularity.py
attacksurfacemeter/utilities.py
attacksurfacemeter.egg-info/PKG-INFO
attacksurfacemeter.egg-info/SOURCES.txt
attacksurfacemeter.egg-info/dependency_links.txt
attacksurfacemeter.egg-info/requires.txt
attacksurfacemeter.egg-info/top_level.txt
attacksurfacemeter/data/android_edge_black_list
attacksurfacemeter/data/android_input_methods
attacksurfacemeter/data/android_output_methods
attacksurfacemeter/data/android_override_input_methods
attacksurfacemeter/data/android_override_output_methods
attacksurfacemeter/data/android_package_black_list
attacksurfacemeter/data/c_dangerous_sys_calls
attacksurfacemeter/data/c_input_functions
attacksurfacemeter/data/c_output_functions
attacksurfacemeter/data/c_std_lib_functions
attacksurfacemeter/data/weights.json
attacksurfacemeter/formatters/__init__.py
attacksurfacemeter/formatters/base_formatter.py
attacksurfacemeter/formatters/html_formatter.py
attacksurfacemeter/formatters/summary_template.html
attacksurfacemeter/formatters/summary_template.txt
attacksurfacemeter/formatters/template.html
attacksurfacemeter/formatters/template.txt
attacksurfacemeter/formatters/txt_formatter.py
attacksurfacemeter/formatters/xml_formatter.py
attacksurfacemeter/loaders/__init__.py
attacksurfacemeter/loaders/base_line_parser.py
attacksurfacemeter/loaders/base_loader.py
attacksurfacemeter/loaders/cflow_line_parser.py
attacksurfacemeter/loaders/cflow_loader.py
attacksurfacemeter/loaders/gprof_line_parser.py
attacksurfacemeter/loaders/gprof_loader.py
attacksurfacemeter/loaders/javacg_line_parser.py
attacksurfacemeter/loaders/javacg_loader.py
attacksurfacemeter/loaders/multigprof_loader.py
attacksurfacemeter/loaders/run_cflow.sh
attacksurfacemeter/loaders/run_cflow_r.sh
attacksurfacemeter/loaders/stack.py