Metadata-Version: 1.1
Name: attacksurfacemeter
Version: 0.11.0
Summary: Library for collecting metrics of the attack surface.
Home-page: https://github.com/andymeneely/attack-surface-metrics
Author: Andy Meneely
Author-email: andy@se.rit.edu
License: The MIT License (MIT) Copyright (c) 2016 Andy Meneely
Platform: UNKNOWN
Classifier: Development Status :: 2 - Pre-Alpha
Classifier: Environment :: Console
Classifier: Intended Audience :: Developers
Classifier: Intended Audience :: Science/Research
Classifier: License :: OSI Approved :: MIT License
Classifier: Natural Language :: English
Classifier: Operating System :: Unix
Classifier: Programming Language :: Python :: 3.5
